nnsight/__init__.py
nnsight/config.yaml
nnsight/ndif.py
nnsight/util.py
nnsight/_c/__init__.py
nnsight/_c/py_mount.c
nnsight/_c/py_mount.cpython-314-x86_64-linux-gnu.so
nnsight/intervention/__init__.py
nnsight/intervention/batching.py
nnsight/intervention/envoy.py
nnsight/intervention/inject.py
nnsight/intervention/interleaver.py
nnsight/intervention/serialization.py
nnsight/intervention/backends/__init__.py
nnsight/intervention/backends/base.py
nnsight/intervention/backends/editing.py
nnsight/intervention/backends/execution.py
nnsight/intervention/backends/remote.py
nnsight/intervention/tracing/__init__.py
nnsight/intervention/tracing/backwards.py
nnsight/intervention/tracing/base.py
nnsight/intervention/tracing/editing.py
nnsight/intervention/tracing/globals.py
nnsight/intervention/tracing/invoker.py
nnsight/intervention/tracing/iterator.py
nnsight/intervention/tracing/tracer.py
nnsight/intervention/tracing/util.py
nnsight/modeling/__init__.py
nnsight/modeling/base.py
nnsight/modeling/diffusion.py
nnsight/modeling/huggingface.py
nnsight/modeling/language.py
nnsight/modeling/transformers.py
nnsight/modeling/mixins/__init__.py
nnsight/modeling/mixins/loadable.py
nnsight/modeling/mixins/meta.py
nnsight/modeling/mixins/remoteable.py
nnsight/modeling/vllm/__init__.py
nnsight/modeling/vllm/batching.py
nnsight/modeling/vllm/sampling.py
nnsight/modeling/vllm/vllm.py
nnsight/modeling/vllm/engines/__init__.py
nnsight/modeling/vllm/engines/engine.py
nnsight/modeling/vllm/model_runners/GPUModelRunner.py
nnsight/modeling/vllm/model_runners/__init__.py
nnsight/modeling/vllm/workers/GPUWorker.py
nnsight/modeling/vllm/workers/__init__.py
nnsight/schema/__init__.py
nnsight/schema/config.py
nnsight/schema/request.py
nnsight/schema/response.py
nnsight-0.5.15.dist-info/METADATA
nnsight-0.5.15.dist-info/WHEEL
nnsight-0.5.15.dist-info/top_level.txt
nnsight-0.5.15.dist-info/RECORD
nnsight-0.5.15.dist-info/licenses/LICENSE
