Metadata-Version: 2.4
Name: nnsight
Version: 0.5.15
Summary: Package for interpreting and manipulating the internals of deep learning models.
Author-email: Jaden Fiotto-Kaufman <jadenfk@outlook.com>
License: MIT License
Project-URL: Homepage, https://github.com/ndif-team/nnsight
Project-URL: Website, https://nnsight.net/
Project-URL: Documentation, https://nnsight.net/documentation/
Project-URL: Changelog, https://github.com/ndif-team/nnsight/CHANGELOG.md
Project-URL: Repository, https://github.com/ndif-team/nnsight.git
Project-URL: Bug Tracker, https://github.com/ndif-team/nnsight/issues
Keywords: deep learning,neural networks,interpretability,pytorch,transformers
Classifier: Development Status :: 4 - Beta
Classifier: Intended Audience :: Developers
Classifier: Intended Audience :: Science/Research
Classifier: Programming Language :: Python :: 3
Classifier: Programming Language :: Python :: 3.10
Classifier: Programming Language :: Python :: 3.11
Classifier: Programming Language :: Python :: 3.12
Classifier: License :: OSI Approved :: MIT License
Classifier: Operating System :: OS Independent
Classifier: Topic :: Scientific/Engineering :: Artificial Intelligence
Requires-Python: >=3.10
License-File: LICENSE
Requires-Dist: transformers
Requires-Dist: astor
Requires-Dist: cloudpickle
Requires-Dist: httpx
Requires-Dist: python-socketio[client]
Requires-Dist: pydantic>=2.9.0
Requires-Dist: torch>=2.4.0
Requires-Dist: accelerate
Requires-Dist: toml
Requires-Dist: ipython
Requires-Dist: rich
Provides-Extra: test
Requires-Dist: pytest>=6.0; extra == "test"
Requires-Dist: pytest-cov; extra == "test"
Provides-Extra: vllm
Requires-Dist: vllm>=0.12; extra == "vllm"
Requires-Dist: triton==3.5.0; extra == "vllm"
Provides-Extra: all
Requires-Dist: nnsight[test,vllm]; extra == "all"
Dynamic: license-file
